README.md
setup.py
mopidy_master/__init__.py
mopidy_master/actor.py
mopidy_master/devicemanager.py
mopidy_master/devicesync.py
mopidy_master/ext.conf
mopidy_master/show-stacktraces.py
mopidy_master/test.py
mopidy_master/test1.py
mopidy_master/web.py
mopidy_master.egg-info/PKG-INFO
mopidy_master.egg-info/SOURCES.txt
mopidy_master.egg-info/dependency_links.txt
mopidy_master.egg-info/entry_points.txt
mopidy_master.egg-info/top_level.txt