Metadata-Version: 2.1
Name: mopidy-master
Version: 1.0
Summary: Mopidy extension to translate music from different sources to satellites
Home-page: https://github.com/stffart/mopidy-master
Author: stffart
Author-email: stffart@gmail.com
License: GPLv3
Platform: UNKNOWN
Classifier: Programming Language :: Python :: 3
